solox/__init__.py
solox/__main__.py
solox/debug.py
solox/web.py
solox/public/__init__.py
solox/public/_iosPerf.py
solox/public/adb.py
solox/public/android_fps.py
solox/public/apm.py
solox/public/apm_pk.py
solox/public/common.py
solox/public/config.json
solox/public/adb/linux/adb
solox/public/adb/linux_arm/adb
solox/public/adb/mac/adb
solox/public/adb/windows/AdbWinApi.dll
solox/public/adb/windows/AdbWinUsbApi.dll
solox/public/adb/windows/adb.exe
solox/public/iosperf/__init__.py
solox/public/iosperf/__main__.py
solox/public/iosperf/_compat.py
solox/public/iosperf/_crash.py
solox/public/iosperf/_device.py
solox/public/iosperf/_hexdump.py
solox/public/iosperf/_imagemounter.py
solox/public/iosperf/_installation.py
solox/public/iosperf/_instruments.py
solox/public/iosperf/_ipautil.py
solox/public/iosperf/_perf.py
solox/public/iosperf/_proto.py
solox/public/iosperf/_relay.py
solox/public/iosperf/_safe_socket.py
solox/public/iosperf/_ssl.py
solox/public/iosperf/_sync.py
solox/public/iosperf/_types.py
solox/public/iosperf/_usbmux.py
solox/public/iosperf/_utils.py
solox/public/iosperf/_version.py
solox/public/iosperf/_wdaproxy.py
solox/public/iosperf/bplist.py
solox/public/iosperf/exceptions.py
solox/public/iosperf/plistlib2.py
solox/public/iosperf/requests_usbmux.py
solox/public/iosperf/struct2.py
solox/public/report_template/android.html
solox/public/report_template/ios.html
solox/public/scrcpy/scrcpy-win32-v2.4/AdbWinApi.dll
solox/public/scrcpy/scrcpy-win32-v2.4/AdbWinUsbApi.dll
solox/public/scrcpy/scrcpy-win32-v2.4/SDL2.dll
solox/public/scrcpy/scrcpy-win32-v2.4/adb.exe
solox/public/scrcpy/scrcpy-win32-v2.4/avcodec-60.dll
solox/public/scrcpy/scrcpy-win32-v2.4/avformat-60.dll
solox/public/scrcpy/scrcpy-win32-v2.4/avutil-58.dll
solox/public/scrcpy/scrcpy-win32-v2.4/icon.png
solox/public/scrcpy/scrcpy-win32-v2.4/libusb-1.0.dll
solox/public/scrcpy/scrcpy-win32-v2.4/open_a_terminal_here.bat
solox/public/scrcpy/scrcpy-win32-v2.4/scrcpy-console.bat
solox-2.9.3.dist-info/LICENSE
solox-2.9.3.dist-info/METADATA
solox-2.9.3.dist-info/WHEEL
solox-2.9.3.dist-info/top_level.txt
solox-2.9.3.dist-info/RECORD
