Metadata-Version: 2.1
Name: solox
Version: 2.9.3
Summary: SoloX - Real-time collection tool for Android/iOS performance data.
Home-page: https://github.com/smart-test-ti/SoloX
Author: Rafa Chen
Author-email: rafacheninc@gamil.com
License: MIT
Classifier: Environment :: Console
Classifier: Intended Audience :: Developers
Classifier: Operating System :: OS Independent
Classifier: Programming Language :: Python :: 3
Requires-Python: >=3.10
License-File: LICENSE
Requires-Dist: flask >=2.0.1
Requires-Dist: requests >=2.28.2
Requires-Dist: logzero
Requires-Dist: Flask-SocketIO ==4.3.1
Requires-Dist: fire
Requires-Dist: python-engineio ==3.13.2
Requires-Dist: python-socketio ==4.6.0
Requires-Dist: Werkzeug ==2.0.3
Requires-Dist: Jinja2 ==3.0.1
Requires-Dist: tidevice ==0.9.7
Requires-Dist: tqdm
Requires-Dist: xlwt
Requires-Dist: pyfiglet
Requires-Dist: psutil
Requires-Dist: opencv-python
